linkbio/__init__.py
linkbio/cli.py
linkbio-1.0.0.dist-info/METADATA
linkbio-1.0.0.dist-info/WHEEL
linkbio-1.0.0.dist-info/entry_points.txt
linkbio-1.0.0.dist-info/top_level.txt
linkbio-1.0.0.dist-info/RECORD
