Metadata-Version: 2.4
Name: linkbio
Version: 1.0.0
Summary: Um gerador de páginas 'link in bio' estáticas em Python.
Author-email: Anderson Braz <contato@andersonbraz.com>
Project-URL: Homepage, https://github.com/andersonbraz/linkbio
Project-URL: Bug Tracker, https://github.com/andersonbraz/linkbio/issues
Requires-Python: >=3.8
Requires-Dist: click
Requires-Dist: pyyaml
Requires-Dist: jinja2
Requires-Dist: requests
